swatch/__init__.py
swatch/cli.py
swatch/swatch.py
adobe_color_swatch-1.0.0.dist-info/LICENSE
adobe_color_swatch-1.0.0.dist-info/METADATA
adobe_color_swatch-1.0.0.dist-info/WHEEL
adobe_color_swatch-1.0.0.dist-info/entry_points.txt
adobe_color_swatch-1.0.0.dist-info/top_level.txt
adobe_color_swatch-1.0.0.dist-info/RECORD
